flet_health/__init__.py
flet_health/flet_health.py
flet_health/health_data_types.py
flutter/flet_health/CHANGELOG.md
flutter/flet_health/LICENSE
flutter/flet_health/README.md
flutter/flet_health/pubspec.lock
flutter/flet_health/pubspec.yaml
flutter/flet_health/lib/flet_health.dart
flutter/flet_health/lib/src/create_control.dart
flutter/flet_health/lib/src/flet_health.dart
flutter/flet_health/lib/src/utils/health_data.dart
flutter/flet_health/lib/src/utils/health_meal_data.dart
flutter/flet_health/lib/src/utils/parsers.dart
flet_health-0.1.1.dist-info/METADATA
flet_health-0.1.1.dist-info/WHEEL
flet_health-0.1.1.dist-info/top_level.txt
flet_health-0.1.1.dist-info/RECORD
