Metadata-Version: 2.4
Name: flet-health
Version: 0.1.1
Summary: FletHealth control for Flet
Author-email: brunobrown <brunobrown.86@gmail.com>
License-Expression: MIT
Project-URL: Homepage, https://github.com/brunobrown/flet-health
Project-URL: Repository, https://github.com/brunobrown/flet-health
Project-URL: Issues, https://github.com/brunobrown/flet-health/issues
Classifier: Topic :: Software Development :: Debuggers
Classifier: Intended Audience :: Developers
Classifier: Natural Language :: English
Classifier: Natural Language :: Portuguese (Brazilian)
Classifier: Operating System :: OS Independent
Classifier: Development Status :: 5 - Production/Stable
Classifier: Programming Language :: Python :: 3.12
Requires-Python: >=3.9
Requires-Dist: flet>=0.25.2
